corrct/__init__.py
corrct/_projector_backends.py
corrct/data_terms.py
corrct/denoisers.py
corrct/filters.py
corrct/models.py
corrct/operators.py
corrct/param_tuning.py
corrct/projectors.py
corrct/regularizers.py
corrct/solvers.py
corrct/struct_illum.py
corrct/testing.py
corrct/alignment/__init__.py
corrct/alignment/centering.py
corrct/alignment/fitting.py
corrct/alignment/shifts.py
corrct/physics/__init__.py
corrct/physics/attenuation.py
corrct/physics/materials.py
corrct/physics/phase.py
corrct/physics/units.py
corrct/physics/xraylib_helper.py
corrct/physics/xrf.py
corrct/processing/__init__.py
corrct/processing/misc.py
corrct/processing/noise.py
corrct/processing/post.py
corrct/processing/pre.py
corrct-2.0.0.dist-info/licenses/LICENSE.md
corrct-2.0.0.dist-info/METADATA
corrct-2.0.0.dist-info/WHEEL
corrct-2.0.0.dist-info/top_level.txt
corrct-2.0.0.dist-info/RECORD
