Metadata-Version: 2.4
Name: corrct
Version: 2.0.0
Summary: Physically corrected projectors for X-ray induced emission CT.
Author-email: Nicola VIGANO <nicola.vigano@cea.fr>
License-Expression: BSD-3-Clause
Project-URL: Homepage, https://github.com/cicwi/PyCorrectedEmissionCT
Project-URL: Documentation, https://cicwi.github.io/PyCorrectedEmissionCT
Project-URL: Changelog, https://cicwi.github.io/PyCorrectedEmissionCT/changelog
Project-URL: Repository, https://github.com/cicwi/PyCorrectedEmissionCT
Project-URL: Issues, https://github.com/cicwi/PyCorrectedEmissionCT/issues
Project-URL: Discussions, https://github.com/cicwi/PyCorrectedEmissionCT/discussions
Classifier: Development Status :: 4 - Beta
Classifier: Intended Audience :: Developers
Classifier: Programming Language :: Python
Classifier: Programming Language :: Python :: 3
Classifier: Programming Language :: Python :: 3 :: Only
Classifier: Programming Language :: Python :: 3.10
Classifier: Programming Language :: Python :: 3.11
Classifier: Programming Language :: Python :: 3.12
Classifier: Programming Language :: Python :: 3.13
Classifier: Topic :: Documentation
Classifier: Topic :: Software Development
Classifier: Topic :: Utilities
Classifier: Typing :: Typed
Requires-Python: >=3.10
License-File: LICENSE.md
Requires-Dist: numpy>=1.21
Requires-Dist: scipy
Requires-Dist: tqdm
Requires-Dist: matplotlib
Requires-Dist: scikit-image
Requires-Dist: pywavelets
Requires-Dist: xraylib
Provides-Extra: dev
Requires-Dist: editables>=0.5; extra == "dev"
Requires-Dist: build>=1.2.2; extra == "dev"
Requires-Dist: git-changelog>=2.4; extra == "dev"
Requires-Dist: twine>=6.1; extra == "dev"
Requires-Dist: isort; extra == "dev"
Requires-Dist: pyupgrade; extra == "dev"
Requires-Dist: pytest>=8.2; extra == "dev"
Requires-Dist: pytest-cov>=5.0; extra == "dev"
Requires-Dist: pytest-randomly>=3.15; extra == "dev"
Requires-Dist: pytest-xdist>=3.6; extra == "dev"
Requires-Dist: pylint; extra == "dev"
Requires-Dist: black>=24.4; extra == "dev"
Requires-Dist: sphinx; extra == "dev"
Requires-Dist: sphinx_rtd_theme; extra == "dev"
Requires-Dist: myst-parser; extra == "dev"
Requires-Dist: sphinx-autodoc2; extra == "dev"
Requires-Dist: sphinx-design; extra == "dev"
Requires-Dist: sphinx-copybutton; extra == "dev"
Requires-Dist: pooch; extra == "dev"
Dynamic: license-file
